MANIFEST.in
README.md
setup.py
airmail/__init__.py
airmail/__version__.py
airmail/cli.py
airmail.egg-info/PKG-INFO
airmail.egg-info/SOURCES.txt
airmail.egg-info/dependency_links.txt
airmail.egg-info/entry_points.txt
airmail.egg-info/requires.txt
airmail.egg-info/top_level.txt
airmail/bash/ecr_push.sh
airmail/commands/__init__.py
airmail/commands/cmd_ecs.py
airmail/data/service.yml
airmail/data/service_update.yml
airmail/data/task.yml
airmail/services/__init__.py
airmail/services/deploy_file.py
airmail/services/ecs_service.py
airmail/services/service_config.py
airmail/services/task_config.py
airmail/services/utils.py
airmail/utils/__init__.py
airmail/utils/bash.py
airmail/utils/config.py
airmail/utils/files.py