Metadata-Version: 2.1
Name: airmail
Version: 0.0.6
Summary: A deploy tool for AWS projects
Home-page: https://github.com/nymag/airmail
Author: Jon Winton
Author-email: jon.winton@nymag.com
License: MIT
Platform: UNKNOWN
Requires-Python: >=3.6.0
